odd_or_even/__init__.py
odd_or_even/checker.py
odd_or_even_808-0.1.0.dist-info/licenses/LICENSE
odd_or_even_808-0.1.0.dist-info/METADATA
odd_or_even_808-0.1.0.dist-info/WHEEL
odd_or_even_808-0.1.0.dist-info/top_level.txt
odd_or_even_808-0.1.0.dist-info/RECORD
