Metadata-Version: 2.4
Name: odd-or-even-808
Version: 0.1.0
Summary: A simple package to check odd or even numbers
Author: Sharvin Vincent
License: MIT
Project-URL: Homepage, https://pypi.org/project/odd-or-even-808/
Project-URL: Source, https://github.com/sharvin808/odd-or-even-808
Requires-Python: >=3.7
License-File: LICENSE
Dynamic: license-file
